src/__init__.py
src/teaching_sim_eval/__init__.py
src/teaching_sim_eval/app.py
src/teaching_sim_eval/myfuncs.py
teaching_sim_eval/__init__.py
teaching_sim_eval/app.py
teaching_sim_eval/myfuncs.py
teaching_sim_eval/static/css
teaching_sim_eval/static/js
teaching_sim_eval/static/styles.css
teaching_sim_eval-0.1.3.dist-info/licenses/LICENSE
teaching_sim_eval-0.1.3.dist-info/METADATA
teaching_sim_eval-0.1.3.dist-info/WHEEL
teaching_sim_eval-0.1.3.dist-info/entry_points.txt
teaching_sim_eval-0.1.3.dist-info/top_level.txt
teaching_sim_eval-0.1.3.dist-info/RECORD
