Metadata-Version: 2.4
Name: teaching_sim_eval
Version: 0.1.3
Summary: Evaluating in-classroom teaching simulations leveraging the power of large language models.
Home-page: https://github.com/xrtze/teaching_sim_eval
Author: Jami Schorling
Author-email: js68jynu@uni-leipzig.de
License: CC BY-NC 4.0
Requires-Python: >=3.12
License-File: LICENSE
Requires-Dist: faicons==0.2.2
Requires-Dist: groq==0.20.0
Requires-Dist: jinja2==3.1.6
Requires-Dist: keyring==25.6.0
Requires-Dist: matplotlib==3.10.1
Requires-Dist: openai==1.93.0
Requires-Dist: pandas==2.2.3
Requires-Dist: pyparsing==3.2.1
Requires-Dist: python-docx==1.1.2
Requires-Dist: shiny==1.4.0
Provides-Extra: dev
Requires-Dist: twine>=4.0.2; extra == "dev"
Dynamic: author
Dynamic: author-email
Dynamic: description
Dynamic: description-content-type
Dynamic: home-page
Dynamic: license
Dynamic: license-file
Dynamic: provides-extra
Dynamic: requires-dist
Dynamic: requires-python
Dynamic: summary
